bootpay/__init__.py
bootpay/bankcode.py
bootpay/client.py
bootpay-1.0.7.dist-info/LICENSE
bootpay-1.0.7.dist-info/METADATA
bootpay-1.0.7.dist-info/WHEEL
bootpay-1.0.7.dist-info/top_level.txt
bootpay-1.0.7.dist-info/RECORD
