Metadata-Version: 2.1
Name: bootpay
Version: 1.0.7
Summary: bootpay server side plugin for python
Home-page: https://github.com/bootpay/backend-python
Author: bootpay <bootpay.co.kr@gmail.com>
License: MIT
Platform: UNKNOWN
Classifier: Development Status :: 5 - Production/Stable
Classifier: Intended Audience :: Developers
Classifier: Topic :: Scientific/Engineering :: Artificial Intelligence
Classifier: Topic :: Scientific/Engineering :: Visualization
Classifier: License :: OSI Approved :: MIT License
Classifier: Programming Language :: Python :: 3.6
Classifier: Operating System :: OS Independent
Requires-Python: >=3
